{
  "metaTitle": "最新 Near 区块 | NearBlocks",
  "metaDescription": "Near 区块链上记录的所有区块信息，包括时间戳、创建者、Gas 使用情况、Gas 价格和交易数量。",
  "blockHeading": "最新 Near 协议区块",
  "listing": "区块 #{from} 到 #{to}（共 {count} 个区块）",
  "blocks": "区块",
  "type": "类型",
  "typeBlock": "区块",
  "typeTxBlock": "交易区块",
  "age": "时间",
  "txn": "交易",
  "miner": "创建者",
  "weight": "权重",
  "volume": "交易量",
  "blockError": "区块错误",
  "block": {
    "metaTitle": "Near 区块 {block} | NearBlocks",
    "metaDescription": "区块高度为 {block} 的 Near 区块信息，包括时间戳、Gas、创建者、交易数和收据。",
    "heading": [
      "区块",
      "#{block}"
    ],
    "height": "区块高度",
    "hash": "哈希",
    "timestamp": "时间戳",
    "transactions": [
      "交易",
      "{txns} 笔交易",
      " 和 {receipts} 笔收据"
    ],
    "fees": "费用",
    "price": "Ⓝ 价格",
    "proof": "证明",
    "gasUsed": "Gas 使用量",
    "gasPrice": "Gas 价格",
    "parenthash": "父哈希",
    "author": "作者",
    "receipts": "收据",
    "gasLimit": "Gas 限额",
    "gasFee": "Gas 费用",
    "listing": "区块 #{from} 到 #{to}（共 {count} 个区块）",
    "txns": "交易"
  },
  "testnetBlockNotice": "[ 这是一个测试网区块 ]",
  "noBlocks": "无区块"
}