{
  "metaTitle": "404 - Halaman Tidak Ditemukan | NearBlocks",
  "metaDescription": "Maaf, kami tidak dapat menemukan konten yang Anda cari. Silakan coba kembali.",
  "description": "<0>Maaf!</0> Terjadi kesalahan tak terduga.",
  "addressDescription": "<0>Maaf!</0> Alamat tidak ditemukan.",
  "blockDescription": "<0>Maaf!</0> Blok tidak ditemukan.",
  "txnDescription": "<0>Maaf!</0> Transaksi tidak ditemukan.",
  "back": "Kembali ke Beranda",
  "tokenDescription": "<0>Maaf!</0> Token tidak ditemukan."
}